{"movies": [{"id": 394775, "id_kinopoisk": 566095, "url": "99683-mechenoscy-2011", "type": "movie", "title": "\u041c\u0435\u0447\u0435\u043d\u043e\u0441\u0446\u044b", "title_alternative": "Wu xia", "tagline": null, "description": "\u0418\u043c\u043f\u0435\u0440\u0438\u044f \u0426\u0438\u043d. \u0421\u043a\u0440\u043e\u043c\u043d\u044b\u0439 \u0440\u0435\u043c\u0435\u0441\u043b\u0435\u043d\u043d\u0438\u043a-\u0438\u0437\u0433\u043e\u0442\u043e\u0432\u0438\u0442\u0435\u043b\u044c \u0431\u0443\u043c\u0430\u0433\u0438 \u0436\u0438\u0432\u0451\u0442 \u0432\u00a0\u0434\u0430\u043b\u0435\u043a\u043e\u0439 \u0434\u0435\u0440\u0435\u0432\u043d\u0435 \u0441\u00a0\u0436\u0435\u043d\u043e\u0439 \u0438\u00a0\u0434\u0432\u0443\u043c\u044f \u0434\u0435\u0442\u044c\u043c\u0438. \u041e\u0434\u043d\u0430\u0436\u0434\u044b \u0432\u00a0\u0434\u0435\u0440\u0435\u0432\u043d\u0435 \u043d\u0435\u043e\u0436\u0438\u0434\u0430\u043d\u043d\u043e \u043f\u043e\u044f\u0432\u043b\u044f\u0435\u0442\u0441\u044f \u0441\u044b\u0449\u0438\u043a, \u0438\u00a0\u0432 \u0438\u0445\u00a0\u0431\u0435\u0437\u043c\u044f\u0442\u0435\u0436\u043d\u043e\u0439 \u0436\u0438\u0437\u043d\u0438 \u043f\u0440\u043e\u0438\u0441\u0445\u043e\u0434\u0438\u0442 \u043f\u0435\u0440\u0435\u0432\u043e\u0440\u043e\u0442.", "year": 2011, "poster": "//images.kinopoisk.cloud/posters/566095.jpg", "trailer": null, "age": null, "actors": ["\u0414\u043e\u043d\u043d\u0438 \u0419\u0435\u043d", "\u0422\u0430\u043d \u0412\u044d\u0439", "\u041b\u0438 \u0426\u0437\u044f-\u043c\u0438\u043d\u044c", "\u0427\u0436\u044d\u043d \u0412\u044d\u0439", "\u0427\u0436\u0430\u043d \u0427\u0436\u044d\u043d-\u044e\u0430\u043d\u044c", "\u042e\u0439 \u041a\u0430\u043d", "\u041a\u044d\u043d\u0434\u0437\u0438 \u0422\u0430\u043d\u0438\u0433\u0430\u043a\u0438", "\u0426\u0438\u043d\u044c \u042f\u043d\u044c", "Du Ning", "\u0418\u043d\u044c \u0421\u044f\u043d\u044c-\u0433\u043e"], "countries": ["\u0413\u043e\u043d\u043a\u043e\u043d\u0433", "\u041a\u0438\u0442\u0430\u0439"], "genres": ["\u0411\u043e\u0435\u0432\u0438\u043a", "\u0422\u0440\u0438\u043b\u043b\u0435\u0440", "\u0414\u0440\u0430\u043c\u0430", "\u041a\u0440\u0438\u043c\u0438\u043d\u0430\u043b"], "directors": ["\u041f\u0438\u0442\u0435\u0440 \u0427\u0430\u043d"], "screenwriters": ["\u041e\u0431\u0440\u0438 \u041b\u0430\u043c", "\u0414\u0436\u043e\u0439\u0441 \u0427\u0430\u043d"], "producers": ["\u0421\u044d\u043c \u0411\u0430\u043d", "\u041f\u0438\u0442\u0435\u0440 \u0427\u0430\u043d", "Ada Yeuk-Jing Foo"], "operators": ["\u041b\u0430\u0439 \u0418\u0443-\u0424\u0430\u0439"], "composers": ["\u041a\u043e\u043c\u0444\u043e\u0440\u0442 \u0427\u0430\u043d", "\u041f\u0438\u0442\u0435\u0440 \u041a\u0430\u043c", "\u0427\u0430\u0440\u0442\u0447\u0430\u0439 \u041f\u043e\u043d\u0433\u043f\u0440\u0430\u043f\u0430\u043f\u0430\u043d"], "painters": ["\u041b\u0438 \u0421\u0443\u043d\u044c", "\u041a\u0435\u043d\u043d\u0435\u0442\u00a0\u0418", "\u0414\u043e\u0440\u0430 \u041d\u0433"], "editors": ["\u0414\u0435\u0440\u0435\u043a \u0425\u0443\u044d\u0439"], "budget": null, "rating_kinopoisk": "7.144", "rating_imdb": "7.1", "kinopoisk_votes": "2761", "imdb_votes": "13221", "fees_world": "$29151995", "fees_russia": null, "premiere_world": "13 \u043c\u0430\u044f 2011", "premiere_russia": null, "frames": ["https://st.kp.yandex.net/im/kadr/1/4/5/kinopoisk.ru-Wu-xia-1457330.jpg", "https://st.kp.yandex.net/im/kadr/1/4/8/kinopoisk.ru-Wu-xia-1489015.jpg", "https://st.kp.yandex.net/im/kadr/1/4/8/kinopoisk.ru-Wu-xia-1489018.jpg", "https://st.kp.yandex.net/im/kadr/1/4/8/kinopoisk.ru-Wu-xia-1489125.jpg", "https://st.kp.yandex.net/im/kadr/1/4/8/kinopoisk.ru-Wu-xia-1489127.jpg", "https://st.kp.yandex.net/im/kadr/1/5/5/kinopoisk.ru-Wu-xia-1558009.jpg", "https://st.kp.yandex.net/im/kadr/1/5/6/kinopoisk.ru-Wu-xia-1560185.jpg", "https://st.kp.yandex.net/im/kadr/1/5/6/kinopoisk.ru-Wu-xia-1560186.jpg", "https://st.kp.yandex.net/im/kadr/1/5/6/kinopoisk.ru-Wu-xia-1560187.jpg", "https://st.kp.yandex.net/im/kadr/1/5/6/kinopoisk.ru-Wu-xia-1560188.jpg", "https://st.kp.yandex.net/im/kadr/1/5/6/kinopoisk.ru-Wu-xia-1560189.jpg", "https://st.kp.yandex.net/im/kadr/1/6/2/kinopoisk.ru-Wu-xia-1625219.jpg", "https://st.kp.yandex.net/im/kadr/1/6/2/kinopoisk.ru-Wu-xia-1625221.jpg", "https://st.kp.yandex.net/im/kadr/1/6/2/kinopoisk.ru-Wu-xia-1625222.jpg", "https://st.kp.yandex.net/im/kadr/1/6/2/kinopoisk.ru-Wu-xia-1625223.jpg", "https://st.kp.yandex.net/im/kadr/1/6/2/kinopoisk.ru-Wu-xia-1625224.jpg", "https://st.kp.yandex.net/im/kadr/1/6/2/kinopoisk.ru-Wu-xia-1625225.jpg", "https://st.kp.yandex.net/im/kadr/1/6/2/kinopoisk.ru-Wu-xia-1625226.jpg", "https://st.kp.yandex.net/im/kadr/1/6/2/kinopoisk.ru-Wu-xia-1625227.jpg", "https://st.kp.yandex.net/im/kadr/1/6/2/kinopoisk.ru-Wu-xia-1625228.jpg", "https://st.kp.yandex.net/im/kadr/1/6/2/kinopoisk.ru-Wu-xia-1625230.jpg", "https://st.kp.yandex.net/im/kadr/1/6/2/kinopoisk.ru-Wu-xia-1625231.jpg", "https://st.kp.yandex.net/im/kadr/1/6/2/kinopoisk.ru-Wu-xia-1625232.jpg", "https://st.kp.yandex.net/im/kadr/1/6/2/kinopoisk.ru-Wu-xia-1625233.jpg", "https://st.kp.yandex.net/im/kadr/1/6/2/kinopoisk.ru-Wu-xia-1625234.jpg", "https://st.kp.yandex.net/im/kadr/1/6/2/kinopoisk.ru-Wu-xia-1625235.jpg", "https://st.kp.yandex.net/im/kadr/1/6/2/kinopoisk.ru-Wu-xia-1625236.jpg", "https://st.kp.yandex.net/im/kadr/1/6/2/kinopoisk.ru-Wu-xia-1625237.jpg", "https://st.kp.yandex.net/im/kadr/1/6/2/kinopoisk.ru-Wu-xia-1625238.jpg", "https://st.kp.yandex.net/im/kadr/1/6/2/kinopoisk.ru-Wu-xia-1625239.jpg", "https://st.kp.yandex.net/im/kadr/1/6/2/kinopoisk.ru-Wu-xia-1625240.jpg", "https://st.kp.yandex.net/im/kadr/1/6/2/kinopoisk.ru-Wu-xia-1625241.jpg", "https://st.kp.yandex.net/im/kadr/1/6/2/kinopoisk.ru-Wu-xia-1625242.jpg", "https://st.kp.yandex.net/im/kadr/1/6/2/kinopoisk.ru-Wu-xia-1625243.jpg", "https://st.kp.yandex.net/im/kadr/1/6/2/kinopoisk.ru-Wu-xia-1625244.jpg", "https://st.kp.yandex.net/im/kadr/1/6/2/kinopoisk.ru-Wu-xia-1625245.jpg", "https://st.kp.yandex.net/im/kadr/1/6/2/kinopoisk.ru-Wu-xia-1625246.jpg", "https://st.kp.yandex.net/im/kadr/1/6/2/kinopoisk.ru-Wu-xia-1625247.jpg", "https://st.kp.yandex.net/im/kadr/1/6/2/kinopoisk.ru-Wu-xia-1625248.jpg", "https://st.kp.yandex.net/im/kadr/1/6/2/kinopoisk.ru-Wu-xia-1625249.jpg", "https://st.kp.yandex.net/im/kadr/1/6/2/kinopoisk.ru-Wu-xia-1625250.jpg", "https://st.kp.yandex.net/im/kadr/1/9/8/kinopoisk.ru-Wu-xia-1983189.jpg", "https://st.kp.yandex.net/im/kadr/1/9/8/kinopoisk.ru-Wu-xia-1983190.jpg", "https://st.kp.yandex.net/im/kadr/1/9/8/kinopoisk.ru-Wu-xia-1983191.jpg"], "screenshots": null, "videocdn": {"url": null, "quality": null, "duration": null, "voice": null}, "hdvb": {"url": null, "quality": null, "duration": null, "voice": null}, "collapse": {"url": null, "quality": null, "duration": null, "voice": null}, "kodik": {"url": null, "quality": null, "duration": null, "voice": null}}, {"id": 119730, "id_kinopoisk": 25205, "url": "163939-emblema-tyazhelogo-roka-1996", "type": "movie", "title": "\u042d\u043c\u0431\u043b\u0435\u043c\u0430 \u0442\u044f\u0436\u0435\u043b\u043e\u0433\u043e \u0440\u043e\u043a\u0430", "title_alternative": "Hard Core Logo", "tagline": "\u00ab4 guys - 5 nights - 3000 miles - 764 gallons of gas - 987 bottles of beer - 3457 cigarettes - 1 last shot\u00bb", "description": "\u0414\u0436\u043e \u0421\u044b\u0449\u0438\u043a, \u0422\u0430\u043b\u0430\u043d\u0442 \u0411\u0438\u043b\u043b\u0438, \u0414\u0436\u043e\u043d \u041e\u043a\u0441\u0435\u043d\u0431\u0435\u0440\u0433\u0435\u0440 \u0438\u00a0\u0412\u043e\u0434\u043e\u043f\u0440\u043e\u0432\u043e\u0434\u0447\u0438\u043a\u00a0\u0097\u00a0\u044d\u0442\u043e \u00ab\u042d\u043c\u0431\u043b\u0435\u043c\u0430 \u0442\u044f\u0436\u0435\u043b\u043e\u0433\u043e \u0440\u043e\u043a\u0430\u00bb, \u043b\u0435\u0433\u0435\u043d\u0434\u0430\u0440\u043d\u0430\u044f \u0412\u0430\u043d\u043a\u0443\u0432\u0435\u0440\u0441\u043a\u0430\u044f \u043f\u0430\u043d\u043a-\u0433\u0440\u0443\u043f\u043f\u0430, \u0437\u0430\u043a\u043e\u043d\u0447\u0438\u0432\u0448\u0430\u044f \u0441\u0432\u043e\u0435 \u0441\u0443\u0449\u0435\u0441\u0442\u0432\u043e\u0432\u0430\u043d\u0438\u0435.\u0414\u0436\u043e \u0443\u0434\u0430\u0435\u0442\u0441\u044f \u0443\u0431\u0435\u0434\u0438\u0442\u044c \u0441\u0432\u043e\u0438\u0445 \u0431\u044b\u0432\u0448\u0438\u0445 \u043f\u0430\u0440\u0442\u043d\u0435\u0440\u043e\u0432 \u043f\u0440\u0435\u043e\u0434\u043e\u043b\u0435\u0442\u044c \u043b\u0438\u0447\u043d\u044b\u0435 \u0440\u0430\u0437\u043d\u043e\u0433\u043b\u0430\u0441\u0438\u044f \u0438\u00a0\u0432\u043d\u043e\u0432\u044c \u043e\u0431\u044a\u0435\u0434\u0438\u043d\u0438\u0442\u044c\u0441\u044f \u0434\u043b\u044f\u00a0\u0435\u0449\u0435 \u043e\u0434\u043d\u043e\u0433\u043e \u043a\u043e\u043d\u0446\u0435\u0440\u0442\u0430, \u0441\u0442\u0430\u0432\u0448\u0435\u0433\u043e \u0443\u0434\u0430\u0447\u043d\u044b\u043c. \u041d\u0435\u043e\u0436\u0438\u0434\u0430\u043d\u043d\u044b\u0439 \u0443\u0441\u043f\u0435\u0445 \u0441\u0443\u043b\u0438\u0442 \u0438\u043c\u00a0\u043d\u0435\u0431\u044b\u0432\u0430\u043b\u044b\u0439 \u0433\u0430\u0441\u0442\u0440\u043e\u043b\u044c\u043d\u044b\u0439 \u0442\u0443\u0440, \u0432\u00a0\u043a\u043e\u0442\u043e\u0440\u043e\u043c \u043c\u044b\u00a0\u0441\u043e\u043f\u0440\u043e\u0432\u043e\u0436\u0434\u0430\u0435\u043c \u0438\u0445\u00a0\u043f\u043e \u0431\u0435\u0441\u043a\u0440\u0430\u0439\u043d\u0438\u043c \u043f\u0440\u043e\u0441\u0442\u043e\u0440\u0430\u043c \u0437\u0430\u043f\u0430\u0434\u043d\u043e\u0439 \u041a\u0430\u043d\u0430\u0434\u044b\u0085", "year": 1996, "poster": "//images.kinopoisk.cloud/posters/25205.jpg", "trailer": "https://www.youtube.com/embed/CAw_HZ4GsFc", "age": "\u0437\u0440\u0438\u0442\u0435\u043b\u044f\u043c, \u0434\u043e\u0441\u0442\u0438\u0433\u0448\u0438\u043c 16 \u043b\u0435\u0442", "actors": ["\u0425\u044c\u044e \u0414\u0438\u043b\u043b\u043e\u043d", "\u041a\u0430\u043b\u043b\u0443\u043c \u041a\u0438\u0442 \u0420\u0435\u043d\u043d\u0438", "\u0414\u0436\u043e\u043d \u041f\u0430\u0439\u043f\u0435\u0440-\u0424\u0435\u0440\u0433\u044e\u0441\u043e\u043d", "\u0411\u0435\u0440\u043d\u0438 \u041a\u043e\u043b\u0441\u043e\u043d", "\u0414\u0436\u0443\u043b\u0438\u0430\u043d \u0420\u0438\u0447\u0438\u043d\u0433\u0441", "\u0411\u0435\u043d\u043d\u0438\u0442\u0430 \u0425\u0430", "\u041a\u043b\u0430\u0443\u0434\u0438\u0430 \u0424\u0435\u0440\u0440\u0438", "\u0414\u0436\u043e\u0443\u0438 \u0420\u0430\u043c\u043e\u043d", "\u041a\u043e\u0440\u0440\u0438\u043d \u041a\u043e\u0441\u043b\u043e", "\u0411\u0440\u044e\u0441 \u041c\u0430\u043a\u0414\u043e\u043d\u0430\u043b\u044c\u0434"], "countries": ["\u041a\u0430\u043d\u0430\u0434\u0430"], "genres": ["\u0414\u0440\u0430\u043c\u0430", "\u041a\u043e\u043c\u0435\u0434\u0438\u044f", "\u041c\u0443\u0437\u044b\u043a\u0430"], "directors": ["\u0411\u0440\u044e\u0441 \u041c\u0430\u043a\u0414\u043e\u043d\u0430\u043b\u044c\u0434"], "screenwriters": ["\u041d\u043e\u044d\u043b\u044c \u0411\u044d\u0439\u043a\u0435\u0440", "\u041c\u0430\u0439\u043a\u043b \u0422\u0435\u0440\u043d\u0435\u0440"], "producers": ["\u0411\u0440\u0430\u0439\u0430\u043d \u0414\u0435\u043d\u043d\u0438\u0441", "\u041a\u0440\u0438\u0441\u0442\u0438\u043d \u0425\u0435\u0431\u043b\u0435\u0440", "\u0414\u0436\u0435\u0439\u043c\u0441 \u0425\u044d\u0434"], "operators": ["\u0414\u044d\u043d\u043d\u0438 \u041d\u043e\u0432\u0430\u043a"], "composers": ["\u0428\u0443\u0430\u043d \u0422\u043e\u0437\u0438\u0440"], "painters": ["\u0414\u044d\u0432\u0438\u0434 \u0412\u0438\u043b\u0441\u043e\u043d", "\u0414\u044d\u0431\u0431\u0438 \u0414\u0436\u043e\u0443", "\u041a\u0430\u0442\u0442\u0435\u0440\u0438\u043d\u0430 \u041a\u0438\u0442"], "editors": ["\u0420\u0435\u0434\u0436\u0438\u043d\u0430\u043b\u044c\u0434 \u0425\u0430\u0440\u043a\u0435\u043c\u0430"], "budget": null, "rating_kinopoisk": "7.144", "rating_imdb": "7.4", "kinopoisk_votes": "210", "imdb_votes": "2489", "fees_world": null, "fees_russia": null, "premiere_world": "20 \u0441\u0435\u043d\u0442\u044f\u0431\u0440\u044f 1996", "premiere_russia": null, "frames": ["https://st.kp.yandex.net/im/kadr/1/5/9/kinopoisk.ru-Hard-Core-Logo-159549.jpg", "https://st.kp.yandex.net/im/kadr/1/5/9/kinopoisk.ru-Hard-Core-Logo-159550.jpg", "https://st.kp.yandex.net/im/kadr/1/5/9/kinopoisk.ru-Hard-Core-Logo-159551.jpg", "https://st.kp.yandex.net/im/kadr/1/5/9/kinopoisk.ru-Hard-Core-Logo-159552.jpg", "https://st.kp.yandex.net/im/kadr/1/5/9/kinopoisk.ru-Hard-Core-Logo-159553.jpg", "https://st.kp.yandex.net/im/kadr/1/5/9/kinopoisk.ru-Hard-Core-Logo-159554.jpg"], "screenshots": null, "videocdn": {"url": null, "quality": null, "duration": null, "voice": null}, "hdvb": {"url": null, "quality": null, "duration": null, "voice": null}, "collapse": {"url": null, "quality": null, "duration": null, "voice": null}, "kodik": {"url": null, "quality": null, "duration": null, "voice": null}}, {"id": 79622, "id_kinopoisk": 114273, "url": "162949-antenna-2007", "type": "movie", "title": "\u0410\u043d\u0442\u0435\u043d\u043d\u0430", "title_alternative": "La antena", "tagline": "\u00abA city without a voice...\u00bb", "description": "\u0412 \u043d\u0435\u043a\u043e\u0435\u043c \u0433\u043e\u0440\u043e\u0434\u0435 \u0436\u0438\u0432\u0443\u0442 \u043b\u044e\u0434\u0438, \u043f\u043e\u0442\u0435\u0440\u044f\u0432\u0448\u0438\u0435 \u0433\u043e\u043b\u043e\u0441\u0430. \u041e\u043d\u0438\u00a0\u043e\u0431\u0449\u0430\u044e\u0442\u0441\u044f \u043c\u0435\u0436\u0434\u0443 \u0441\u043e\u0431\u043e\u0439, \u0447\u0438\u0442\u0430\u044f \u043f\u043e\u00a0\u0433\u0443\u0431\u0430\u043c, \u0446\u0435\u043b\u044b\u043c\u0438 \u0434\u043d\u044f\u043c\u0438 \u0441\u043c\u043e\u0442\u0440\u044f\u0442 \u0442\u0435\u043b\u0435\u0432\u0438\u0437\u043e\u0440, \u0435\u0434\u044f\u0442 \u043e\u0434\u043d\u0443 \u0438\u00a0\u0442\u0443 \u0436\u0435\u00a0\u043f\u0438\u0449\u0443, \u0436\u0438\u0437\u043d\u044c \u0438\u0445\u00a0\u043e\u0434\u043d\u043e\u043e\u0431\u0440\u0430\u0437\u043d\u0430 \u0438\u00a0\u043f\u0443\u0441\u0442\u0430. \u0413\u043e\u043b\u043e\u0441\u0430 \u0443\u00a0\u043b\u044e\u0434\u0435\u0439 \u0443\u043a\u0440\u0430\u043b \u041c\u0438\u0441\u0442\u0435\u0440 \u0422\u0412\u00a0\u0097\u00a0\u043f\u0440\u0430\u0432\u0438\u0442\u0435\u043b\u044c \u0433\u043e\u0440\u043e\u0434\u0430. \u0418\u043c\u0435\u043d\u043d\u043e \u0447\u0435\u043b\u043e\u0432\u0435\u0447\u0435\u0441\u043a\u0438\u0435 \u0433\u043e\u043b\u043e\u0441\u0430 \u043f\u043e\u0434\u043f\u0438\u0442\u044b\u0432\u0430\u044e\u0442 \u0441\u0438\u0441\u0442\u0435\u043c\u0443, \u043a\u043e\u0442\u043e\u0440\u0430\u044f \u0434\u0435\u0440\u0436\u0438\u0442 \u0433\u043e\u0440\u043e\u0434 \u0432\u00a0\u0430\u0431\u0441\u043e\u043b\u044e\u0442\u043d\u043e\u0439 \u0432\u043b\u0430\u0441\u0442\u0438 \u041c\u0438\u0441\u0442\u0435\u0440\u0430 \u0422\u0412. \u041e\u0434\u043d\u0430\u043a\u043e \u043e\u043d\u00a0\u0445\u043e\u0447\u0435\u0442 \u0443\u043a\u0440\u0430\u0441\u0442\u044c \u0443\u00a0\u043b\u044e\u0434\u0435\u0439 \u0438\u00a0\u0441\u043b\u043e\u0432\u0430, \u0438\u00a0\u0447\u0442\u043e\u0431\u044b \u0434\u043e\u0431\u0438\u0442\u044c\u0441\u044f \u044d\u0442\u043e\u0433\u043e, \u041c\u0438\u0441\u0442\u0435\u0440 \u0422\u0412\u00a0\u043f\u043e\u0445\u0438\u0449\u0430\u0435\u0442 \u043f\u0435\u0432\u0438\u0446\u0443 \u0413\u043e\u043b\u043e\u0441, \u0435\u0434\u0438\u043d\u0441\u0442\u0432\u0435\u043d\u043d\u043e\u0433\u043e \u0447\u0435\u043b\u043e\u0432\u0435\u043a\u0430 \u0432\u00a0\u0433\u043e\u0440\u043e\u0434\u0435, \u0441\u043e\u0445\u0440\u0430\u043d\u0438\u0432\u0448\u0435\u0433\u043e \u0441\u043f\u043e\u0441\u043e\u0431\u043d\u043e\u0441\u0442\u044c \u0433\u043e\u0432\u043e\u0440\u0438\u0442\u044c.", "year": 2007, "poster": "//images.kinopoisk.cloud/posters/114273.jpg", "trailer": "https://www.youtube.com/embed/iXAMzt4iJ7o", "age": null, "actors": ["\u0412\u0430\u043b\u0435\u0440\u0438\u044f \u0411\u0435\u0440\u0442\u0443\u0447\u0435\u043b\u043b\u0438", "\u0410\u043b\u0435\u0445\u0430\u043d\u0434\u0440\u043e \u0423\u0440\u0434\u0430\u043f\u0438\u043b\u044c\u0435\u0442\u0430", "\u0425\u0443\u043b\u044c\u0435\u0442\u0430 \u041a\u0430\u0440\u0434\u0438\u043d\u0430\u043b\u0438", "\u0420\u0430\u0444\u0430\u044d\u043b\u044c \u0424\u0435\u0440\u0440\u043e", "\u0424\u043b\u043e\u0440\u0435\u043d\u0446\u0438\u044f \u0420\u0430\u0433\u0433\u0438", "\u0421\u043e\u043b \u041c\u043e\u0440\u0435\u043d\u043e", "\u0414\u0436\u043e\u043d\u0430\u0442\u0430\u043d \u0421\u044d\u043d\u0434\u043e\u0440", "\u0420\u0430\u0443\u043b\u044c \u0425\u043e\u0447\u043c\u0430\u043d", "\u0420\u0438\u043a\u0430\u0440\u0434\u043e \u041c\u0435\u0440\u043a\u0438\u043d", "Carlos Pi\u00f1eyro"], "countries": ["\u0410\u0440\u0433\u0435\u043d\u0442\u0438\u043d\u0430"], "genres": ["\u0424\u0430\u043d\u0442\u0430\u0441\u0442\u0438\u043a\u0430", "\u0424\u044d\u043d\u0442\u0435\u0437\u0438", "\u0414\u0440\u0430\u043c\u0430"], "directors": ["\u042d\u0441\u0442\u0435\u0431\u0430\u043d \u0421\u0430\u043f\u0438\u0440"], "screenwriters": ["\u042d\u0441\u0442\u0435\u0431\u0430\u043d \u0421\u0430\u043f\u0438\u0440"], "producers": ["Gonzalo Agulla", "Jos\u00e9 Arnal", "\u0424\u0435\u0434\u0435\u0440\u0438\u043a\u043e \u0420\u043e\u0442\u0441\u0442\u0435\u0439\u043d"], "operators": ["\u041a\u0440\u0438\u0441\u0442\u0438\u0430\u043d \u041a\u043e\u0442\u0442\u0435\u0442"], "composers": ["\u041b\u0435\u043e \u0421\u0443\u0445\u0430\u0442\u043e\u0432\u0438\u0447"], "painters": ["\u0414\u0430\u043d\u0438\u044d\u043b\u044c \u0413\u0438\u043c\u0435\u043b\u044c\u0431\u0435\u0440\u0433", "\u0410\u043d\u0434\u0440\u0435\u0430 \u041c\u0430\u0442\u0442\u0438\u043e", "\u0412\u0430\u043b\u0435\u043d\u0442\u0438\u043d\u0430 \u041b\u043b\u043e\u0440\u0435\u043d\u0441"], "editors": ["\u041f\u0430\u0431\u043b\u043e \u0411\u0430\u0440\u0431\u0438\u0435\u0440\u0438 \u041a\u0430\u0440\u0440\u0435\u0440\u0430"], "budget": null, "rating_kinopoisk": "7.144", "rating_imdb": "7.4", "kinopoisk_votes": "1497", "imdb_votes": "3643", "fees_world": null, "fees_russia": null, "premiere_world": "24 \u044f\u043d\u0432\u0430\u0440\u044f 2007", "premiere_russia": null, "frames": ["https://st.kp.yandex.net/im/kadr/8/1/9/kinopoisk.ru-La-antena-819047.jpg", "https://st.kp.yandex.net/im/kadr/8/1/9/kinopoisk.ru-La-antena-819049.jpg", "https://st.kp.yandex.net/im/kadr/8/1/9/kinopoisk.ru-La-antena-819050.jpg", "https://st.kp.yandex.net/im/kadr/8/1/9/kinopoisk.ru-La-antena-819051.jpg", "https://st.kp.yandex.net/im/kadr/8/1/9/kinopoisk.ru-La-antena-819052.jpg", "https://st.kp.yandex.net/im/kadr/8/1/9/kinopoisk.ru-La-antena-819053.jpg", "https://st.kp.yandex.net/im/kadr/8/4/1/kinopoisk.ru-La-antena-841398.jpg", "https://st.kp.yandex.net/im/kadr/8/4/1/kinopoisk.ru-La-antena-841404.jpg", "https://st.kp.yandex.net/im/kadr/8/4/1/kinopoisk.ru-La-antena-841406.jpg", "https://st.kp.yandex.net/im/kadr/8/4/1/kinopoisk.ru-La-antena-841407.jpg", "https://st.kp.yandex.net/im/kadr/1/9/2/kinopoisk.ru-La-antena-1924334.jpg", "https://st.kp.yandex.net/im/kadr/1/9/2/kinopoisk.ru-La-antena-1924335.jpg", "https://st.kp.yandex.net/im/kadr/1/9/2/kinopoisk.ru-La-antena-1924336.jpg", "https://st.kp.yandex.net/im/kadr/1/9/2/kinopoisk.ru-La-antena-1924337.jpg", "https://st.kp.yandex.net/im/kadr/1/9/2/kinopoisk.ru-La-antena-1924338.jpg", "https://st.kp.yandex.net/im/kadr/1/9/2/kinopoisk.ru-La-antena-1924339.jpg", "https://st.kp.yandex.net/im/kadr/1/9/2/kinopoisk.ru-La-antena-1924340.jpg", "https://st.kp.yandex.net/im/kadr/1/9/2/kinopoisk.ru-La-antena-1924341.jpg", "https://st.kp.yandex.net/im/kadr/1/9/2/kinopoisk.ru-La-antena-1924342.jpg", "https://st.kp.yandex.net/im/kadr/1/9/2/kinopoisk.ru-La-antena-1924343.jpg", "https://st.kp.yandex.net/im/kadr/1/9/2/kinopoisk.ru-La-antena-1924344.jpg"], "screenshots": null, "videocdn": {"url": null, "quality": null, "duration": null, "voice": null}, "hdvb": {"url": null, "quality": null, "duration": null, "voice": null}, "collapse": {"url": null, "quality": null, "duration": null, "voice": null}, "kodik": {"url": null, "quality": null, "duration": null, "voice": null}}, {"id": 67239, "id_kinopoisk": 80758, "url": "596431-peter-1934", "type": "movie", "title": "\u041f\u0435\u0442\u0435\u0440", "title_alternative": "Peter", "tagline": null, "description": "\u0422\u0440\u0443\u0434\u043d\u044b\u0435 \u0432\u0440\u0435\u043c\u0435\u043d\u0430 \u043d\u0430\u0441\u0442\u0430\u043b\u0438 \u0434\u043b\u044f\u00a0\u0434\u0435\u0434\u0443\u0448\u043a\u0438 \u0438\u00a0\u0435\u0433\u043e \u044e\u043d\u043e\u0439 \u0432\u043d\u0443\u0447\u043a\u0438 \u0415\u0432\u044b\u00a0\u0097\u00a0\u043e\u043d\u0438 \u0431\u0440\u043e\u0448\u0435\u043d\u044b \u043d\u0430\u00a0\u0443\u043b\u0438\u0446\u0443 \u0437\u0430\u00a0\u043d\u0435\u0443\u043f\u043b\u0430\u0442\u0443 \u0436\u0438\u043b\u044c\u044f. \u0422\u0435\u043f\u0435\u0440\u044c \u0438\u043c\u00a0\u043f\u0440\u0438\u0434\u0435\u0442\u0441\u044f \u043f\u0435\u0442\u044c \u043f\u0435\u0441\u043d\u0438 \u043d\u0430\u00a0\u0443\u043b\u0438\u0446\u0430\u0445 \u0438\u00a0\u043f\u0440\u043e\u0441\u0438\u0442\u044c \u043c\u0438\u043b\u043e\u0441\u0442\u044b\u043d\u044e. \u041e\u0434\u043d\u0430\u0436\u0434\u044b \u0431\u0435\u0433\u043b\u044b\u0439 \u043f\u0440\u0435\u0441\u0442\u0443\u043f\u043d\u0438\u043a \u0437\u0430\u0431\u0440\u0430\u043b \u0435\u0434\u0438\u043d\u0441\u0442\u0432\u0435\u043d\u043d\u043e\u0435 \u043f\u043b\u0430\u0442\u044c\u0435 \u0443\u00a0\u0434\u0435\u0432\u0443\u0448\u043a\u0438, \u0438\u00a0\u043e\u043d\u0430 \u0432\u044b\u043d\u0443\u0436\u0434\u0435\u043d\u0430 \u043f\u0435\u0440\u0435\u043e\u0434\u0435\u0442\u044c\u0441\u044f \u0432\u00a0\u0431\u0440\u043e\u0448\u0435\u043d\u043d\u044b\u0439 \u0438\u043c\u00a0\u0431\u0440\u044e\u0447\u043d\u044b\u0439 \u043a\u043e\u0441\u0442\u044e\u043c. \u0421\u00a0\u044d\u0442\u043e\u0433\u043e \u043c\u043e\u043c\u0435\u043d\u0442\u0430 \u0415\u0432\u0430\u00a0\u0441\u0442\u0430\u043d\u043e\u0432\u0438\u0442\u0441\u044f \u041f\u0435\u0442\u0435\u0440\u043e\u043c\u0085", "year": 1934, "poster": "//images.kinopoisk.cloud/posters/80758.jpg", "trailer": null, "age": "\u0434\u043b\u044f \u043b\u044e\u0431\u043e\u0439 \u0437\u0440\u0438\u0442\u0435\u043b\u044c\u0441\u043a\u043e\u0439 \u0430\u0443\u0434\u0438\u0442\u043e\u0440\u0438\u0438", "actors": ["\u0424\u0440\u0430\u043d\u0446\u0438\u0441\u043a\u0430 \u0413\u0430\u0430\u043b\u044c", "\u0424\u0435\u043b\u0438\u043a\u0441 \u0411\u0440\u0435\u0441\u0441\u0430\u0440\u0442", "\u0424\u0440\u0438\u0434\u043b\u044c \u0428\u0435\u043f\u0430", "\u0420\u0438\u0445\u0430\u0440\u0434 \u042d\u0439\u0431\u043d\u0435\u0440", "\u0413\u0430\u043d\u0441 \u042f\u0440\u0430\u0439", "\u0421\u0438\u0433\u0443\u0440\u0434 \u041b\u043e\u0434\u0435", "\u0413\u0440\u0435\u0442\u0435 \u041d\u0430\u0446\u043b\u0435\u0440", "\u0410\u043d\u0442\u043e\u043d \u041f\u043e\u0438\u043d\u0442\u043d\u0435\u0440", "\u0413\u0430\u043d\u0441 \u0420\u0438\u0445\u0442\u0435\u0440", "\u0418\u043c\u0440\u0435 \u0420\u0430\u0434\u0430\u0438"], "countries": ["\u0410\u0432\u0441\u0442\u0440\u0438\u044f", "\u0412\u0435\u043d\u0433\u0440\u0438\u044f"], "genres": ["\u041c\u044e\u0437\u0438\u043a\u043b", "\u041a\u043e\u043c\u0435\u0434\u0438\u044f"], "directors": ["\u0413\u0435\u043d\u0440\u0438 \u041a\u043e\u0441\u0442\u0435\u0440"], "screenwriters": ["\u0424\u0435\u043b\u0438\u043a\u0441 \u0414\u0436\u0435\u043a\u0441\u043e\u043d", "\u0418\u043e\u0433\u0430\u043d\u043d \u0444\u043e\u043d \u0412\u0430\u0448\u0430\u0440\u0438", "\u0428\u0430\u043d\u0434\u043e\u0440 \u041d\u0430\u0434\u0430\u0448"], "producers": ["\u0414\u0436\u043e \u041f\u0430\u0441\u0442\u0435\u0440\u043d\u0430\u043a"], "operators": ["\u0418\u0448\u0442\u0432\u0430\u043d \u042d\u0439\u0431\u0435\u043d"], "composers": ["\u041d\u0438\u043a\u043e\u043b\u0430\u0441 \u0411\u0440\u043e\u0434\u0441\u043a\u0438\u0439"], "painters": ["\u041c\u0430\u0440\u0442\u043e\u043d \u0412\u0438\u043d\u0446\u0435"], "editors": ["\u0412\u0438\u043a\u0442\u043e\u0440 \u0413\u0435\u0440\u0442\u043b\u0435\u0440"], "budget": null, "rating_kinopoisk": "7.144", "rating_imdb": "7.3", "kinopoisk_votes": "81", "imdb_votes": "48", "fees_world": null, "fees_russia": null, "premiere_world": "20 \u0434\u0435\u043a\u0430\u0431\u0440\u044f 1934", "premiere_russia": null, "frames": ["https://st.kp.yandex.net/im/kadr/2/0/7/kinopoisk.ru-Peter-2079242.jpg", "https://st.kp.yandex.net/im/kadr/2/0/7/kinopoisk.ru-Peter-2079243.jpg", "https://st.kp.yandex.net/im/kadr/2/0/7/kinopoisk.ru-Peter-2079244.jpg"], "screenshots": null, "videocdn": {"url": null, "quality": null, "duration": null, "voice": null}, "hdvb": {"url": null, "quality": null, "duration": null, "voice": null}, "collapse": {"url": null, "quality": null, "duration": null, "voice": null}, "kodik": {"url": null, "quality": null, "duration": null, "voice": null}}, {"id": 39149, "id_kinopoisk": 34432, "url": "462772-semya-1986", "type": "movie", "title": "\u0421\u0435\u043c\u044c\u044f", "title_alternative": "La famiglia", "tagline": "\u00abIn 1906 Carlo was born into a very large family, a family of artists and lovers, spinsters and fools. Now he&#039;s 80...and they&#039;re all coming to dinner\u00bb", "description": "\u0421\u0432\u043e\u0435\u043e\u0431\u0440\u0430\u0437\u043d\u0430\u044f \u0447\u0430\u0441\u0442\u043d\u0430\u044f \u0445\u0440\u043e\u043d\u0438\u043a\u0430 20\u00a0\u0432\u0435\u043a\u0430, \u0438\u0441\u0442\u043e\u0440\u0438\u044f \u043e\u0434\u043d\u043e\u0439 \u0438\u0442\u0430\u043b\u044c\u044f\u043d\u0441\u043a\u043e\u0439 \u0441\u0435\u043c\u044c\u0438 \u0441\u00a01906 \u0434\u043e\u00a01986 \u0433\u043e\u0434\u0430, \u043b\u044e\u0431\u043e\u0432\u043d\u044b\u0435 \u0438\u00a0\u0436\u0438\u0442\u0435\u0439\u0441\u043a\u0438\u0435 \u043f\u0435\u0440\u0438\u043f\u0435\u0442\u0438\u0438 \u0432\u00a0\u0436\u0438\u0437\u043d\u0438 \u043f\u0440\u043e\u0444\u0435\u0441\u0441\u043e\u0440\u0430 \u043b\u0438\u0442\u0435\u0440\u0430\u0442\u0443\u0440\u044b \u041a\u0430\u0440\u043b\u043e. \u041a\u0430\u0436\u0435\u0442\u0441\u044f, \u043f\u043e\u0447\u0442\u0438 \u043d\u0438\u0447\u0435\u0433\u043e \u043d\u0435\u00a0\u043f\u0440\u043e\u0438\u0441\u0445\u043e\u0434\u0438\u0442 \u0432\u00a0\u0441\u0442\u0430\u0440\u043e\u043c \u0441\u0435\u043c\u0435\u0439\u043d\u043e\u043c \u0434\u043e\u043c\u0435 \u0432\u00a0\u0420\u0438\u043c\u0435\u00a0\u0097\u00a0\u0442\u0435\u0447\u0435\u0442 \u043e\u0431\u044b\u0447\u043d\u0430\u044f \u0436\u0438\u0437\u043d\u044c. \u041a\u0442\u043e-\u0442\u043e \u0440\u043e\u0436\u0434\u0430\u0435\u0442\u0441\u044f, \u043f\u043e\u0434\u0440\u0430\u0441\u0442\u0430\u0435\u0442, \u0441\u043e\u0447\u0435\u0442\u0430\u0435\u0442\u0441\u044f \u0431\u0440\u0430\u043a\u043e\u043c, \u0443\u0445\u043e\u0434\u0438\u0442 \u043d\u0430\u00a0\u0444\u0440\u043e\u043d\u0442, \u0438\u0449\u0435\u0442 \u0440\u0430\u0431\u043e\u0442\u0443, \u043f\u0435\u0440\u0435\u0436\u0438\u0432\u0430\u0435\u0442 \u043b\u0438\u0447\u043d\u044b\u0435 \u043d\u0435\u0443\u0440\u044f\u0434\u0438\u0446\u044b, \u0432\u043a\u043b\u044e\u0447\u0430\u0435\u0442\u0441\u044f \u0432\u00a0\u043f\u043e\u043b\u0438\u0442\u0438\u0447\u0435\u0441\u043a\u0438\u0435 \u0441\u043f\u043e\u0440\u044b, \u0432\u0441\u043a\u043e\u0440\u0435 \u0432\u043e\u0432\u0441\u0435 \u043e\u00a0\u043d\u0438\u0445 \u043f\u043e\u0437\u0430\u0431\u044b\u0432, \u043f\u043e\u0441\u0442\u0435\u043f\u0435\u043d\u043d\u043e \u0441\u0442\u0430\u0440\u0435\u0435\u0442, \u0430\u00a0\u043f\u043e\u0442\u043e\u043c \u0432\u0437\u0438\u0440\u0430\u0435\u0442 \u0441\u00a0\u043d\u0435\u0434\u043e\u0443\u043c\u0435\u043d\u0438\u0435\u043c \u043d\u0430\u00a0\u043f\u0440\u043e\u0448\u043b\u043e\u0435: \u0430\u00a0\u0431\u044b\u043b\u0430 \u043b\u0438\u00a0\u0436\u0438\u0437\u043d\u044c?! \u0418\u00a0\u0442\u043e\u043b\u044c\u043a\u043e \u043c\u043d\u043e\u0433\u043e\u0447\u0438\u0441\u043b\u0435\u043d\u043d\u044b\u0435 \u0440\u043e\u0434\u0441\u0442\u0432\u0435\u043d\u043d\u0438\u043a\u0438, \u0441\u043e\u0431\u0440\u0430\u0432\u0448\u0438\u0435\u0441\u044f \u043d\u0430\u00a080-\u043b\u0435\u0442\u0438\u0435 \u0433\u043b\u0430\u0432\u044b \u0434\u043e\u043c\u0430, \u0437\u0430\u043f\u0435\u0447\u0430\u0442\u043b\u0435\u043d\u043d\u044b\u0435 \u043d\u0430\u00a0\u043e\u0447\u0435\u0440\u0435\u0434\u043d\u043e\u0439 \u0441\u0435\u043c\u0435\u0439\u043d\u043e\u0439 \u0444\u043e\u0442\u043e\u0433\u0440\u0430\u0444\u0438\u0438, \u043f\u043e\u0434\u0442\u0432\u0435\u0440\u0436\u0434\u0430\u044e\u0442 \u0441\u0432\u043e\u0438\u043c \u043f\u0440\u0438\u0441\u0443\u0442\u0441\u0442\u0432\u0438\u0435\u043c, \u0447\u0442\u043e\u00a0\u0441 \u043c\u043e\u043c\u0435\u043d\u0442\u0430 \u043f\u0435\u0440\u0432\u043e\u0433\u043e \u043f\u043e\u044f\u0432\u043b\u0435\u043d\u0438\u044f \u0433\u0435\u0440\u043e\u044f \u043d\u0430\u00a0\u044d\u043a\u0440\u0430\u043d\u0435 \u0435\u0449\u0435\u00a0\u0432 \u043c\u043b\u0430\u0434\u0435\u043d\u0447\u0435\u0441\u0442\u0432\u0435 \u043f\u0440\u043e\u0448\u043b\u043e \u043e\u0447\u0435\u043d\u044c \u043c\u043d\u043e\u0433\u043e \u043b\u0435\u0442\u00a0\u0097\u00a0\u0438 \u0441\u043c\u0435\u043d\u0438\u043b\u043e\u0441\u044c \u043d\u0435\u0441\u043a\u043e\u043b\u044c\u043a\u043e \u043f\u043e\u043a\u043e\u043b\u0435\u043d\u0438\u0439.", "year": 1986, "poster": "//images.kinopoisk.cloud/posters/34432.jpg", "trailer": null, "age": null, "actors": ["\u042d\u043c\u0430\u043d\u0443\u044d\u043b\u0435 \u041b\u0430\u043c\u0430\u0440\u043e", "\u0410\u043d\u0434\u0440\u0435\u0430 \u041e\u043a\u043a\u0438\u043f\u0438\u043d\u0442\u0438", "\u0412\u0438\u0442\u0442\u043e\u0440\u0438\u043e \u0413\u0430\u0441\u0441\u043c\u0430\u043d", "\u0427\u0435\u0447\u0438\u043b\u0438\u044f \u0414\u0430\u0446\u0446\u0438", "\u0421\u0442\u0435\u0444\u0430\u043d\u0438\u044f \u0421\u0430\u043d\u0434\u0440\u0435\u043b\u043b\u0438", "\u0414\u0436\u043e \u0427\u0430\u043c\u043f\u0430", "\u0424\u0430\u043d\u043d\u0438 \u0410\u0440\u0434\u0430\u043d", "\u0419\u043e\u0448\u043a\u0430 \u0412\u0435\u0440\u0441\u0430\u0440\u0438", "\u0410\u043b\u044c\u0431\u0435\u0440\u0442\u043e \u0414\u0436\u0438\u043c\u0438\u043d\u044c\u044f\u043d\u0438", "\u041c\u0430\u0441\u0441\u0438\u043c\u043e \u0414\u0430\u043f\u043f\u043e\u0440\u0442\u043e"], "countries": ["\u0418\u0442\u0430\u043b\u0438\u044f", "\u0424\u0440\u0430\u043d\u0446\u0438\u044f"], "genres": ["\u0414\u0440\u0430\u043c\u0430", "\u041c\u0435\u043b\u043e\u0434\u0440\u0430\u043c\u0430"], "directors": ["\u042d\u0442\u0442\u043e\u0440\u0435 \u0421\u043a\u043e\u043b\u0430"], "screenwriters": ["\u0413\u0440\u0430\u0446\u0438\u0430\u043d\u043e \u0414\u0438\u0430\u043d\u0430", "\u0420\u0443\u0434\u0436\u0435\u0440\u043e \u041c\u0430\u043a\u043a\u0430\u0440\u0438", "\u0424\u0443\u0440\u0438\u043e \u0421\u043a\u0430\u0440\u043f\u0435\u043b\u043b\u0438"], "producers": ["\u0424\u0440\u0430\u043d\u043a\u043e \u041a\u043e\u043c\u043c\u0438\u0442\u0442\u0435\u0440\u0438"], "operators": ["\u0420\u0438\u043a\u0430\u0440\u0434\u043e \u0410\u0440\u043e\u043d\u043e\u0432\u0438\u0447"], "composers": ["\u0410\u0440\u043c\u0430\u043d\u0434\u043e \u0422\u0440\u043e\u0432\u0430\u0439\u043e\u043b\u0438"], "painters": ["\u0421\u0438\u043d\u0446\u0438\u044f \u041b\u043e \u0424\u0430\u0437\u0438\u043e", "\u041b\u0443\u0447\u0438\u0430\u043d\u043e \u0420\u0438\u0447\u0447\u0435\u0440\u0438", "\u0413\u0430\u0431\u0440\u0438\u044d\u043b\u043b\u0430 \u041f\u0435\u0441\u043a\u0443\u0447\u0447\u0438"], "editors": ["\u0424\u0440\u0430\u043d\u0447\u0435\u0441\u043a\u043e \u041c\u0430\u043b\u044c\u0432\u0435\u0441\u0442\u0438\u0442\u043e", "\u042d\u0442\u0442\u043e\u0440\u0435 \u0421\u043a\u043e\u043b\u0430"], "budget": null, "rating_kinopoisk": "7.144", "rating_imdb": "7.4", "kinopoisk_votes": "181", "imdb_votes": "1881", "fees_world": null, "fees_russia": null, "premiere_world": "20 \u044f\u043d\u0432\u0430\u0440\u044f 1987", "premiere_russia": null, "frames": ["https://st.kp.yandex.net/im/kadr/1/3/6/kinopoisk.ru-La-famiglia-1362194.jpg", "https://st.kp.yandex.net/im/kadr/1/3/6/kinopoisk.ru-La-famiglia-1362195.jpg", "https://st.kp.yandex.net/im/kadr/1/3/6/kinopoisk.ru-La-famiglia-1362196.jpg", "https://st.kp.yandex.net/im/kadr/1/3/6/kinopoisk.ru-La-famiglia-1362197.jpg", "https://st.kp.yandex.net/im/kadr/1/3/6/kinopoisk.ru-La-famiglia-1362198.jpg", "https://st.kp.yandex.net/im/kadr/1/3/6/kinopoisk.ru-La-famiglia-1362199.jpg", "https://st.kp.yandex.net/im/kadr/1/5/6/kinopoisk.ru-La-famiglia-1560113.jpg"], "screenshots": null, "videocdn": {"url": null, "quality": null, "duration": null, "voice": null}, "hdvb": {"url": null, "quality": null, "duration": null, "voice": null}, "collapse": {"url": null, "quality": null, "duration": null, "voice": null}, "kodik": {"url": null, "quality": null, "duration": null, "voice": null}}, {"id": 38608, "id_kinopoisk": 45032, "url": "550100-kuznechik-1978", "type": "movie", "title": "\u041a\u0443\u0437\u043d\u0435\u0447\u0438\u043a", "title_alternative": null, "tagline": null, "description": "\u041e\u043a\u043e\u043d\u0447\u0438\u0432 \u0448\u043a\u043e\u043b\u0443, \u041b\u0435\u043d\u0430 \u041a\u0443\u0437\u043d\u0435\u0446\u043e\u0432\u0430 \u043f\u0440\u0438\u0435\u0445\u0430\u043b\u0430 \u0432\u00a0\u041c\u043e\u0441\u043a\u0432\u0443 \u0438\u00a0\u0431\u0435\u0437 \u043e\u0441\u043e\u0431\u044b\u0445 \u0442\u0440\u0443\u0434\u043d\u043e\u0441\u0442\u0435\u0439 \u043f\u043e\u0441\u0442\u0443\u043f\u0438\u043b\u0430 \u0432\u00a0\u043f\u0435\u0434\u0438\u043d\u0441\u0442\u0438\u0442\u0443\u0442. \u0421\u0442\u0430\u0432 \u0441\u0442\u0443\u0434\u0435\u043d\u0442\u043a\u043e\u0439 \u0444\u0438\u043b\u0444\u0430\u043a\u0430, \u043e\u043d\u0430\u00a0\u0447\u0435\u0442\u043a\u043e \u0441\u0444\u043e\u0440\u043c\u0443\u043b\u0438\u0440\u043e\u0432\u0430\u043b\u0430 \u0431\u043b\u0438\u0436\u0430\u0439\u0448\u0443\u044e \u0446\u0435\u043b\u044c\u00a0\u0097\u00a0\u043b\u044e\u0431\u043e\u0439 \u0446\u0435\u043d\u043e\u0439 \u0434\u043e\u0441\u0442\u0438\u0447\u044c \u043c\u0430\u0442\u0435\u0440\u0438\u0430\u043b\u044c\u043d\u043e\u0433\u043e \u0431\u043b\u0430\u0433\u043e\u043f\u043e\u043b\u0443\u0447\u0438\u044f \u0438\u00a0\u0441\u0434\u0435\u043b\u0430\u0442\u044c \u043a\u0430\u0440\u044c\u0435\u0440\u0443. \u0412\u044b\u0439\u0434\u044f \u0437\u0430\u043c\u0443\u0436 \u0437\u0430\u00a0\u0441\u0442\u0430\u0440\u0448\u0435\u0433\u043e \u043d\u0430\u0443\u0447\u043d\u043e\u0433\u043e \u0441\u043e\u0442\u0440\u0443\u0434\u043d\u0438\u043a\u0430, \u041b\u0435\u043d\u0430 \u0441\u0440\u0430\u0437\u0443 \u0436\u0435\u00a0\u043f\u043e\u043b\u0443\u0447\u0438\u043b\u0430 \u043a\u0432\u0430\u0440\u0442\u0438\u0440\u0443, \u043c\u0430\u0448\u0438\u043d\u0443 \u0438\u00a0\u043f\u043e\u043a\u043b\u043e\u043d\u043d\u0438\u043a\u043e\u0432. \u0410\u00a0\u043f\u0435\u0440\u0432\u0430\u044f \u0435\u0435\u00a0\u0438\u0437\u043c\u0435\u043d\u0430 \u043f\u0440\u0438\u043d\u0435\u0441\u043b\u0430 \u0436\u0435\u043b\u0430\u0435\u043c\u044b\u0439 \u0440\u0435\u0437\u0443\u043b\u044c\u0442\u0430\u0442\u00a0\u0097\u00a0\u0440\u0430\u0437\u0432\u043e\u0434 \u0438\u00a0\u0435\u0434\u0438\u043d\u043e\u043b\u0438\u0447\u043d\u043e\u0435 \u0432\u043b\u0430\u0434\u0435\u043d\u0438\u0435 \u0438\u043c\u0443\u0449\u0435\u0441\u0442\u0432\u043e\u043c\u0085", "year": 1978, "poster": "//images.kinopoisk.cloud/posters/45032.jpg", "trailer": "https://www.youtube.com/embed/FKhRJuAEaAM", "age": "\u0437\u0440\u0438\u0442\u0435\u043b\u044f\u043c, \u0434\u043e\u0441\u0442\u0438\u0433\u0448\u0438\u043c 12 \u043b\u0435\u0442", "actors": ["\u041b\u044e\u0434\u043c\u0438\u043b\u0430 \u041d\u0438\u043b\u044c\u0441\u043a\u0430\u044f", "\u041d\u0438\u043a\u043e\u043b\u0430\u0439 \u0418\u0432\u0430\u043d\u043e\u0432", "\u041b\u044e\u0434\u043c\u0438\u043b\u0430 \u0410\u0440\u0438\u043d\u0438\u043d\u0430", "\u0410\u043d\u0430\u0442\u043e\u043b\u0438\u0439 \u0420\u043e\u043c\u0430\u0448\u0438\u043d", "\u041c\u0430\u0440\u0438\u043d\u0430 \u041b\u0435\u0432\u0442\u043e\u0432\u0430", "\u0412\u044f\u0447\u0435\u0441\u043b\u0430\u0432 \u0411\u0430\u0440\u0430\u043d\u043e\u0432", "\u0412\u043b\u0430\u0434\u0438\u043c\u0438\u0440 \u0413\u0440\u0430\u043c\u043c\u0430\u0442\u0438\u043a\u043e\u0432", "\u0410\u043d\u0430\u0442\u043e\u043b\u0438\u0439 \u0421\u043a\u043e\u0440\u044f\u043a\u0438\u043d", "\u041e\u043b\u044c\u0433\u0430 \u0422\u043e\u043f\u0438\u043b\u0438\u043d\u0430", "\u0415\u043b\u0435\u043d\u0430 \u0418\u0432\u043e\u0447\u043a\u0438\u043d\u0430"], "countries": ["\u0421\u0421\u0421\u0420"], "genres": ["\u0414\u0440\u0430\u043c\u0430"], "directors": ["\u0411\u043e\u0440\u0438\u0441 \u0413\u0440\u0438\u0433\u043e\u0440\u044c\u0435\u0432"], "screenwriters": ["\u0424\u0435\u043b\u0438\u043a\u0441 \u041c\u0438\u0440\u043e\u043d\u0435\u0440"], "producers": null, "operators": ["\u0418\u0433\u043e\u0440\u044c \u041a\u043b\u0435\u0431\u0430\u043d\u043e\u0432"], "composers": ["\u0413\u0435\u043e\u0440\u0433\u0438\u0439 \u0414\u043c\u0438\u0442\u0440\u0438\u0435\u0432"], "painters": ["\u041d\u043e\u0439 \u0421\u0435\u043d\u0434\u0435\u0440\u043e\u0432"], "editors": null, "budget": null, "rating_kinopoisk": "7.144", "rating_imdb": "7", "kinopoisk_votes": "293", "imdb_votes": "22", "fees_world": null, "fees_russia": null, "premiere_world": "14 \u043c\u0430\u044f 1979", "premiere_russia": null, "frames": null, "screenshots": null, "videocdn": {"url": null, "quality": null, "duration": null, "voice": null}, "hdvb": {"url": null, "quality": null, "duration": null, "voice": null}, "collapse": {"url": null, "quality": null, "duration": null, "voice": null}, "kodik": {"url": null, "quality": null, "duration": null, "voice": null}}, {"id": 23574, "id_kinopoisk": 16505, "url": "240254-bolshoy-obman-1949", "type": "movie", "title": "\u0411\u043e\u043b\u044c\u0448\u043e\u0439 \u043e\u0431\u043c\u0430\u043d", "title_alternative": "The Big Steal", "tagline": "\u00abMitchum is HOT! - HOT...off location in the heart of Mexico...HOT...after a girl with a million-dollar figure!...HOT...at the nation&#039;s boxoffices...HOT...in his newest picture!\u00bb", "description": "\u041d\u0430 \u043f\u044b\u043b\u044c\u043d\u044b\u0445 \u0438\u00a0\u0440\u0430\u0437\u0431\u0438\u0442\u044b\u0445 \u043c\u0435\u043a\u0441\u0438\u043a\u0430\u043d\u0441\u043a\u0438\u0445 \u0434\u043e\u0440\u043e\u0433\u0430\u0445 \u0440\u0430\u0437\u0432\u043e\u0440\u0430\u0447\u0438\u0432\u0430\u0435\u0442\u0441\u044f \u043f\u043e\u0433\u043e\u043d\u044f. \u0411\u0430\u0431\u043d\u0438\u043a\u0430 \u0438\u00a0\u0433\u0440\u0430\u0431\u0438\u0442\u0435\u043b\u044f \u0414\u0436\u0438\u043c\u0430 \u0424\u0438\u0441\u043a\u0435 \u0434\u043e\u0433\u043e\u043d\u044f\u044e\u0442 \u0435\u0433\u043e\u00a0\u043d\u0435\u0432\u0435\u0441\u0442\u0430 \u0438\u00a0\u0447\u0435\u043b\u043e\u0432\u0435\u043a, \u043f\u0440\u0435\u0434\u0441\u0442\u0430\u0432\u043b\u044f\u044e\u0449\u0438\u0439\u0441\u044f \u043a\u0430\u043f\u0438\u0442\u0430\u043d\u043e\u043c \u0430\u043c\u0435\u0440\u0438\u043a\u0430\u043d\u0441\u043a\u043e\u0439 \u0430\u0440\u043c\u0438\u0438 \u0412\u0438\u043d\u0441\u0435\u043d\u0442\u043e\u043c \u0411\u043b\u0435\u0439\u043a\u043e\u043c, \u0437\u0430\u00a0\u043d\u0438\u043c\u0438 \u0433\u043e\u043d\u0438\u0442\u0441\u044f \u043d\u0430\u0441\u0442\u043e\u044f\u0449\u0438\u0439 \u043a\u0430\u043f\u0438\u0442\u0430\u043d \u0411\u043b\u0435\u0439\u043a, \u0430\u00a0\u043d\u0430 \u0445\u0432\u043e\u0441\u0442\u0435 \u0443\u00a0\u0432\u0441\u0435\u0445\u00a0\u0097\u00a0\u043c\u0435\u043a\u0441\u0438\u043a\u0430\u043d\u0441\u043a\u0430\u044f \u043f\u043e\u043b\u0438\u0446\u0438\u044f.", "year": 1949, "poster": "//images.kinopoisk.cloud/posters/16505.jpg", "trailer": null, "age": null, "actors": ["\u0420\u043e\u0431\u0435\u0440\u0442 \u041c\u0438\u0442\u0447\u0435\u043c", "\u0414\u0436\u0435\u0439\u043d \u0413\u0440\u0438\u0440", "\u0423\u0438\u043b\u044c\u044f\u043c \u0411\u0435\u043d\u0434\u0438\u043a\u0441", "\u041f\u0430\u0442\u0440\u0438\u043a \u041d\u043e\u0443\u043b\u0437", "\u0420\u0430\u043c\u043e\u043d \u041d\u043e\u0432\u0430\u0440\u0440\u043e", "\u0414\u043e\u043d \u0410\u043b\u044c\u0432\u0430\u0440\u0430\u0434\u043e", "\u0414\u0436\u043e\u043d \u041a\u0432\u043e\u043b\u0435\u043d", "\u041f\u0430\u0441\u043a\u0443\u0430\u043b\u044c \u0413\u0430\u0440\u0441\u0438\u044f \u041f\u0435\u043d\u044c\u044f", "\u0413\u0440\u0435\u0433\u043e\u0440\u0438\u043e \u0410\u043a\u043e\u0441\u0442\u0430", "\u0421\u0430\u043b\u044c\u0432\u0430\u0434\u043e\u0440 \u0411\u0430\u0433\u0435\u0441"], "countries": ["\u0421\u0428\u0410"], "genres": ["\u0424\u0438\u043b\u044c\u043c-\u043d\u0443\u0430\u0440", "\u0422\u0440\u0438\u043b\u043b\u0435\u0440", "\u041c\u0435\u043b\u043e\u0434\u0440\u0430\u043c\u0430", "\u041a\u0440\u0438\u043c\u0438\u043d\u0430\u043b"], "directors": ["\u0414\u043e\u043d \u0421\u0438\u0433\u0435\u043b"], "screenwriters": ["\u0414\u044d\u043d\u0438\u044d\u043b \u041c\u044d\u0439\u043d\u0443\u043e\u0440\u0438\u043d\u0433", "\u0414\u0436\u0435\u0440\u0430\u043b\u044c\u0434 \u0414\u0440\u044d\u0439\u0441\u043e\u043d \u0410\u0434\u0430\u043c\u0441", "\u0420\u0438\u0447\u0430\u0440\u0434 \u0423\u043e\u0440\u043c\u0441\u0435\u0440"], "producers": ["\u0414\u0436\u0435\u043a \u0414\u0436. \u0413\u0440\u043e\u0441\u0441", "\u0421\u0438\u0434 \u0420\u043e\u0433\u0435\u043b\u043b"], "operators": ["\u0413\u0430\u0440\u0440\u0438 \u0414\u0436. \u0412\u0430\u0439\u043b\u0434"], "composers": ["\u041b\u0438 \u0425\u0430\u0440\u043b\u0430\u0439\u043d"], "painters": ["\u0420\u0430\u043b\u044c\u0444 \u0411\u0435\u0440\u0433\u0435\u0440", "\u0410\u043b\u044c\u0431\u0435\u0440\u0442 \u0421. \u0414\u2019\u0410\u0433\u043e\u0441\u0442\u0438\u043d\u043e", "\u042d\u0434\u0432\u0430\u0440\u0434 \u0421\u0442\u0438\u0432\u0435\u043d\u0441\u043e\u043d"], "editors": ["\u0421\u044d\u043c\u044e\u044d\u043b \u0418. \u0411\u0438\u0442\u043b\u0438"], "budget": null, "rating_kinopoisk": "7.144", "rating_imdb": "7", "kinopoisk_votes": "124", "imdb_votes": "3937", "fees_world": null, "fees_russia": null, "premiere_world": "1 \u0438\u044e\u043b\u044f 1949", "premiere_russia": null, "frames": null, "screenshots": null, "videocdn": {"url": null, "quality": null, "duration": null, "voice": null}, "hdvb": {"url": null, "quality": null, "duration": null, "voice": null}, "collapse": {"url": null, "quality": null, "duration": null, "voice": null}, "kodik": {"url": null, "quality": null, "duration": null, "voice": null}}, {"id": 22557, "id_kinopoisk": 15807, "url": "520027-kroliki-2002", "type": "movie", "title": "\u041a\u0440\u043e\u043b\u0438\u043a\u0438", "title_alternative": "Rabbits", "tagline": null, "description": "\u0424\u0438\u043b\u044c\u043c, \u0441\u043e\u0441\u0442\u043e\u044f\u0449\u0438\u0439 \u0438\u0437\u00a0\u0432\u043e\u0441\u044c\u043c\u0438 \u044d\u043f\u0438\u0437\u043e\u0434\u043e\u0432 \u043e\u00a0\u043f\u043e\u0432\u0441\u0435\u0434\u043d\u0435\u0432\u043d\u043e\u0439 \u0436\u0438\u0437\u043d\u0438 \u043b\u044e\u0434\u0435\u0439, \u043f\u0435\u0440\u0435\u043e\u0434\u0435\u0442\u044b\u0445 \u043a\u0440\u043e\u043b\u0438\u043a\u0430\u043c\u0438. \u041a\u0430\u0436\u0434\u044b\u0439 \u044d\u043f\u0438\u0437\u043e\u0434 \u043f\u043e\u043a\u0430\u0437\u044b\u0432\u0430\u0435\u0442 \u043d\u0435\u043a\u0443\u044e \u043a\u043e\u043c\u043d\u0430\u0442\u0443 \u0438\u00a0\u0441\u043e\u0434\u0435\u0440\u0436\u0438\u0442 \u0441\u043a\u0435\u0442\u0447\u0438 \u0441\u00a0\u043d\u0435\u043e\u0436\u0438\u0434\u0430\u043d\u043d\u044b\u043c\u0438 \u0434\u0438\u0430\u043b\u043e\u0433\u0430\u043c\u0438 \u0442\u0440\u0451\u0445 \u043b\u044e\u0434\u0435\u0439-\u043a\u0440\u043e\u043b\u0438\u043a\u043e\u0432, \u043a\u0430\u0436\u0434\u044b\u0439 \u0438\u0437\u00a0\u043a\u043e\u0442\u043e\u0440\u044b\u0445 \u0432\u0435\u0434\u0435\u0442 \u0441\u0432\u043e\u044e \u0441\u043e\u0431\u0441\u0442\u0432\u0435\u043d\u043d\u0443\u044e \u0438\u0433\u0440\u0443. \u00ab\u041a\u0440\u043e\u043b\u0438\u043a\u0438\u00bb \u0441\u043e\u043f\u0440\u043e\u0432\u043e\u0436\u0434\u0435\u043d\u044b \u043c\u0440\u0430\u0447\u043d\u044b\u043c\u0438 \u0442\u0438\u0442\u0440\u0430\u043c\u0438: \u00ab\u0412 \u0431\u0435\u0437\u044b\u043c\u044f\u043d\u043d\u043e\u043c \u0433\u043e\u0440\u043e\u0434\u0435, \u043f\u043e\u0440\u0430\u0436\u0451\u043d\u043d\u043e\u043c \u043d\u0435\u043f\u0440\u0435\u043a\u0440\u0430\u0449\u0430\u044e\u0449\u0438\u043c\u0441\u044f \u0434\u043e\u0436\u0434\u0435\u043c\u0085 \u0432\u00a0\u0441\u0442\u0440\u0430\u0448\u043d\u043e\u0439 \u0444\u0430\u043d\u0442\u0430\u0437\u0438\u0438 \u0436\u0438\u0432\u0443\u0442 \u0442\u0440\u0438\u00a0\u043a\u0440\u043e\u043b\u0438\u043a\u0430\u00bb.", "year": 2002, "poster": "//images.kinopoisk.cloud/posters/15807.jpg", "trailer": null, "age": null, "actors": ["\u0421\u043a\u043e\u0442\u0442 \u041a\u043e\u0444\u0444\u0438", "\u041b\u0430\u0443\u0440\u0430 \u0425\u044d\u0440\u0440\u0438\u043d\u0433", "\u041d\u0430\u043e\u043c\u0438 \u0423\u043e\u0442\u0442\u0441", "\u0420\u0435\u0431\u0435\u043a\u0430 \u0414\u0435\u043b\u044c \u0420\u0438\u043e"], "countries": ["\u0421\u0428\u0410"], "genres": ["\u041a\u043e\u0440\u043e\u0442\u043a\u043e\u043c\u0435\u0442\u0440\u0430\u0436\u043a\u0430", "\u0423\u0436\u0430\u0441\u044b", "\u0424\u044d\u043d\u0442\u0435\u0437\u0438", "\u0422\u0440\u0438\u043b\u043b\u0435\u0440", "\u0414\u0440\u0430\u043c\u0430", "\u0414\u0435\u0442\u0435\u043a\u0442\u0438\u0432"], "directors": ["\u0414\u044d\u0432\u0438\u0434 \u041b\u0438\u043d\u0447"], "screenwriters": ["\u0414\u044d\u0432\u0438\u0434 \u041b\u0438\u043d\u0447"], "producers": null, "operators": null, "composers": ["\u0410\u043d\u0434\u0436\u0435\u043b\u043e \u0411\u0430\u0434\u0430\u043b\u0430\u043c\u0435\u043d\u0442\u0438"], "painters": ["Tony Candelaria"], "editors": null, "budget": null, "rating_kinopoisk": "7.144", "rating_imdb": "7", "kinopoisk_votes": "3411", "imdb_votes": "6763", "fees_world": null, "fees_russia": null, "premiere_world": null, "premiere_russia": null, "frames": ["https://st.kp.yandex.net/im/kadr/5/8/2/kinopoisk.ru-Rabbits-582632.jpg", "https://st.kp.yandex.net/im/kadr/5/8/2/kinopoisk.ru-Rabbits-582633.jpg", "https://st.kp.yandex.net/im/kadr/5/8/2/kinopoisk.ru-Rabbits-582634.jpg"], "screenshots": ["https://st.kp.yandex.net/im/kadr/3/3/5/kinopoisk.ru-Rabbits-3352317.jpg", "https://st.kp.yandex.net/im/kadr/3/3/5/kinopoisk.ru-Rabbits-3352318.jpg", "https://st.kp.yandex.net/im/kadr/3/3/5/kinopoisk.ru-Rabbits-3352319.jpg", "https://st.kp.yandex.net/im/kadr/3/3/5/kinopoisk.ru-Rabbits-3352320.jpg", "https://st.kp.yandex.net/im/kadr/3/3/5/kinopoisk.ru-Rabbits-3352321.jpg", "https://st.kp.yandex.net/im/kadr/3/3/5/kinopoisk.ru-Rabbits-3352322.jpg", "https://st.kp.yandex.net/im/kadr/3/3/5/kinopoisk.ru-Rabbits-3352323.jpg", "https://st.kp.yandex.net/im/kadr/3/3/5/kinopoisk.ru-Rabbits-3352324.jpg", "https://st.kp.yandex.net/im/kadr/3/3/5/kinopoisk.ru-Rabbits-3352325.jpg", "https://st.kp.yandex.net/im/kadr/3/3/5/kinopoisk.ru-Rabbits-3352326.jpg", "https://st.kp.yandex.net/im/kadr/3/3/5/kinopoisk.ru-Rabbits-3352327.jpg", "https://st.kp.yandex.net/im/kadr/3/3/5/kinopoisk.ru-Rabbits-3352328.jpg", "https://st.kp.yandex.net/im/kadr/3/3/5/kinopoisk.ru-Rabbits-3352329.jpg", "https://st.kp.yandex.net/im/kadr/3/3/5/kinopoisk.ru-Rabbits-3352330.jpg", "https://st.kp.yandex.net/im/kadr/3/3/5/kinopoisk.ru-Rabbits-3352331.jpg", "https://st.kp.yandex.net/im/kadr/3/3/5/kinopoisk.ru-Rabbits-3352332.jpg"], "videocdn": {"url": null, "quality": null, "duration": null, "voice": null}, "hdvb": {"url": null, "quality": null, "duration": null, "voice": null}, "collapse": {"url": null, "quality": null, "duration": null, "voice": null}, "kodik": {"url": null, "quality": null, "duration": null, "voice": null}}, {"id": 15516, "id_kinopoisk": 3617, "url": "519018-krug-druzey-1995", "type": "movie", "title": "\u041a\u0440\u0443\u0433 \u0434\u0440\u0443\u0437\u0435\u0439", "title_alternative": "Circle of Friends", "tagline": "\u00abSometimes dreams do come true\u00bb", "description": "\u0414\u0435\u0439\u0441\u0442\u0432\u0438\u0435 \u0444\u0438\u043b\u044c\u043c\u0430, \u043f\u043e\u0441\u0442\u0430\u0432\u043b\u0435\u043d\u043d\u043e\u0433\u043e \u043f\u043e\u00a0\u0440\u043e\u043c\u0430\u043d\u0443 \u041c\u044d\u0432\u0438 \u0411\u0438\u043d\u0447\u0438, \u043d\u0430\u0447\u0438\u043d\u0430\u0435\u0442\u0441\u044f \u0432\u00a0\u0418\u0440\u043b\u0430\u043d\u0434\u0438\u0438 1949 \u0433\u043e\u0434\u0430 \u0438\u00a0\u043f\u0435\u0440\u0435\u043c\u0435\u0449\u0430\u0435\u0442\u0441\u044f \u0432\u00a01957 \u0433\u043e\u0434. \u041c\u044b\u00a0\u0437\u043d\u0430\u043a\u043e\u043c\u0438\u043c\u0441\u044f \u0441\u00a0\u0442\u0440\u0435\u043c\u044f \u043f\u043e\u0434\u0440\u0443\u0433\u0430\u043c\u0438 \u0438\u00a0\u0443\u0437\u043d\u0430\u0435\u043c \u0438\u0445\u00a0\u0447\u0435\u0440\u0435\u0437 \u0432\u043e\u0441\u043f\u0440\u0438\u044f\u0442\u0438\u0435, \u0432\u00a0\u043e\u0441\u043d\u043e\u0432\u043d\u043e\u043c, \u043e\u0434\u043d\u043e\u0439 \u0438\u0437\u00a0\u043d\u0438\u0445, \u043a\u0440\u0443\u043f\u043d\u043e\u0439, \u043d\u0435\u043a\u0440\u0430\u0441\u0438\u0432\u043e\u0439, \u043d\u043e\u00a0\u043d\u0435\u043e\u0440\u0434\u0438\u043d\u0430\u0440\u043d\u043e\u0439 \u0434\u0435\u0432\u0443\u0448\u043a\u0438 \u0411\u0435\u043d\u043d\u0438, \u0441\u00a0\u0436\u0438\u0432\u044b\u043c \u0443\u043c\u043e\u043c \u0438\u00a0\u0431\u043e\u043b\u044c\u0448\u0438\u043c \u0431\u044e\u0441\u0442\u043e\u043c. \u0415\u0439 \u043d\u0440\u0430\u0432\u0438\u0442\u0441\u044f \u043a\u0440\u0430\u0441\u0438\u0432\u044b\u0439 \u043c\u043e\u043b\u043e\u0434\u043e\u0439 \u043f\u0430\u0440\u0435\u043d\u044c \u0414\u0436\u0435\u043a \u0438\u0437\u00a0\u0438\u0445 \u0436\u0435\u00a0\u043a\u043e\u043b\u043b\u0435\u0434\u0436\u0430, \u0438\u00a0\u0435\u043c\u0443 \u0441\u00a0\u043d\u0435\u0439 \u043f\u0440\u043e\u0441\u0442\u043e \u0438\u00a0\u043b\u0435\u0433\u043a\u043e. \u041e\u043d\u00a0\u0441\u0430\u043c \u043f\u0440\u0438\u0437\u043d\u0430\u0435\u0442\u0441\u044f, \u0447\u0442\u043e\u00a0\u043c\u043e\u0436\u0435\u0442 \u0433\u043e\u0432\u043e\u0440\u0438\u0442\u044c \u0441\u00a0\u043d\u0435\u0439 \u043e\u00a0\u0442\u0430\u043a\u0438\u0445 \u0432\u0435\u0449\u0430\u0445, \u043e\u00a0\u043a\u0430\u043a\u0438\u0445 \u043d\u0438\u043a\u043e\u0433\u0434\u0430 \u043d\u0435\u00a0\u0441\u043c\u043e\u0433 \u0431\u044b\u00a0\u0433\u043e\u0432\u043e\u0440\u0438\u0442\u044c \u0441\u00a0\u043a\u0435\u043c-\u043d\u0438\u0431\u0443\u0434\u044c \u0434\u0440\u0443\u0433\u0438\u043c. \u0415\u0435\u00a0\u043a\u0440\u0430\u0441\u0438\u0432\u0430\u044f \u043f\u043e\u0434\u0440\u0443\u0433\u0430 \u0437\u0430\u0431\u0435\u0440\u0435\u043c\u0435\u043d\u0435\u043b\u0430, \u0430\u00a0\u043a\u043e\u0433\u0434\u0430 \u0435\u0435\u00a0\u043b\u044e\u0431\u043e\u0432\u043d\u0438\u043a \u0431\u0440\u043e\u0441\u0438\u043b \u0435\u0435, \u0434\u0430\u0432\u00a0\u0434\u0435\u043d\u0435\u0433 \u043d\u0430\u00a0\u0430\u0431\u043e\u0440\u0442, \u043e\u043d\u0430\u00a0\u0441\u043e\u0431\u043b\u0430\u0437\u043d\u0438\u043b\u0430 \u0414\u0436\u0435\u043a\u0430, \u043e\u0431\u044a\u044f\u0432\u0438\u0432, \u0447\u0442\u043e\u00a0\u0440\u0435\u0431\u0435\u043d\u043e\u043a \u043e\u0442\u00a0\u043d\u0435\u0433\u043e.\u00a0", "year": 1995, "poster": "//images.kinopoisk.cloud/posters/3617.jpg", "trailer": null, "age": "\u0437\u0440\u0438\u0442\u0435\u043b\u044f\u043c, \u0434\u043e\u0441\u0442\u0438\u0433\u0448\u0438\u043c 12 \u043b\u0435\u0442", "actors": ["\u041a\u0440\u0438\u0441 \u041e\u2019\u0414\u043e\u043d\u043d\u0435\u043b\u043b", "\u041c\u0438\u043d\u043d\u0438 \u0414\u0440\u0430\u0439\u0432\u0435\u0440", "\u0414\u0436\u0435\u0440\u0430\u043b\u044c\u0434\u0438\u043d \u041e\u2019\u0420\u043e\u0443", "\u0421\u0430\u0444\u0444\u0440\u043e\u043d \u0411\u0435\u0440\u0440\u043e\u0443\u0437", "\u0410\u043b\u0430\u043d \u041a\u0430\u043c\u043c\u0438\u043d\u0433", "\u041a\u043e\u043b\u0438\u043d \u0424\u0451\u0440\u0442", "\u042d\u0439\u0434\u0430\u043d \u0413\u0438\u043b\u043b\u0435\u043d", "\u041c\u0438\u043a \u041b\u044d\u043b\u043b\u0438", "\u0411\u0440\u0438\u0442\u0442\u0430 \u0421\u043c\u0438\u0442", "\u0414\u0436\u043e\u043d \u041a\u044d\u0432\u044d\u043d\u0430"], "countries": ["\u0418\u0440\u043b\u0430\u043d\u0434\u0438\u044f", "\u0421\u0428\u0410", "\u0412\u0435\u043b\u0438\u043a\u043e\u0431\u0440\u0438\u0442\u0430\u043d\u0438\u044f"], "genres": ["\u0414\u0440\u0430\u043c\u0430", "\u041c\u0435\u043b\u043e\u0434\u0440\u0430\u043c\u0430"], "directors": ["\u041f\u044d\u0442 \u041e\u2019\u041a\u043e\u043d\u043d\u043e\u0440"], "screenwriters": ["\u042d\u043d\u0434\u0440\u044e \u0414\u044d\u0432\u0438\u0441", "\u041c\u044d\u0432\u0438 \u0411\u0438\u043d\u0447\u0438"], "producers": ["\u0424\u0440\u044d\u043d\u043a \u041f\u0440\u0430\u0439\u0441", "\u0410\u0440\u043b\u0438\u043d \u0421\u0435\u043b\u043b\u0435\u0440\u0441", "\u0410\u043b\u0435\u043a\u0441 \u0412\u0438\u043d\u0438\u0446\u043a\u0438"], "operators": ["\u041a\u0435\u043d\u043d\u0435\u0442 \u041c\u0430\u043a\u041c\u0438\u043b\u043b\u0430\u043d"], "composers": ["\u041c\u0430\u0439\u043a\u043b \u041a\u044d\u043c\u0435\u043d"], "painters": ["\u0414\u0436\u0438\u043c \u041a\u043b\u044d\u0439", "\u041a\u0440\u0438\u0441 \u0421\u0438\u0433\u0435\u0440\u0441", "\u0410\u043d\u0443\u0448\u0438\u0430 \u041d\u0435\u0440\u0430\u0434\u0436\u0438\u043a"], "editors": ["\u0414\u0436\u043e\u043d \u0414\u0436\u0438\u043c\u043f\u0441\u043e\u043d"], "budget": null, "rating_kinopoisk": "7.144", "rating_imdb": "6.6", "kinopoisk_votes": "732", "imdb_votes": "7791", "fees_world": null, "fees_russia": null, "premiere_world": "2 \u043c\u0430\u0440\u0442\u0430 1995", "premiere_russia": null, "frames": null, "screenshots": null, "videocdn": {"url": null, "quality": null, "duration": null, "voice": null}, "hdvb": {"url": null, "quality": null, "duration": null, "voice": null}, "collapse": {"url": null, "quality": null, "duration": null, "voice": null}, "kodik": {"url": null, "quality": null, "duration": null, "voice": null}}, {"id": 550563, "id_kinopoisk": 13964, "url": "446267-ombre-otvazhnyy-strelok-1967", "type": "movie", "title": "\u041e\u043c\u0431\u0440\u0435: \u041e\u0442\u0432\u0430\u0436\u043d\u044b\u0439 \u0441\u0442\u0440\u0435\u043b\u043e\u043a", "title_alternative": "Hombre", "tagline": "\u00abHombre means MAN... Paul Newman is HOMBRE!\u00bb", "description": "\u041a\u043e\u0433\u0434\u0430 \u0414\u0436\u043e\u043d \u0420\u0430\u0441\u0441\u0435\u043b\u00a0\u0097\u00a0\u0431\u0435\u043b\u044b\u0439 \u0430\u043c\u0435\u0440\u0438\u043a\u0430\u043d\u0435\u0446, \u0432\u043e\u0441\u043f\u0438\u0442\u0430\u043d\u043d\u044b\u0439 \u0432\u00a0\u0410\u0440\u0438\u0437\u043e\u043d\u0435 \u0438\u043d\u0434\u0435\u0439\u0441\u043a\u0438\u043c \u043f\u043b\u0435\u043c\u0435\u043d\u0435\u043c, \u043f\u0440\u043e\u0434\u0430\u0435\u0442 \u043d\u0435\u0431\u043e\u043b\u044c\u0448\u0443\u044e \u0433\u043e\u0441\u0442\u0438\u043d\u0438\u0446\u0443, \u0434\u043e\u0441\u0442\u0430\u0432\u0448\u0443\u044e\u0441\u044f \u043e\u0442\u00a0\u043e\u0442\u0446\u0430, \u043e\u043d\u00a0\u0432\u044b\u043d\u0443\u0436\u0434\u0435\u043d \u0432\u0441\u0442\u0443\u043f\u0438\u0442\u044c \u0432\u00a0\u043a\u043e\u043d\u0444\u043b\u0438\u043a\u0442 \u0441\u00a0\u043e\u0431\u0449\u0435\u0441\u0442\u0432\u043e\u043c, \u043a\u043e\u0442\u043e\u0440\u043e\u0435 \u0441\u0430\u043c\u00a0\u043f\u0440\u0435\u0437\u0438\u0440\u0430\u0435\u0442, \u0414\u0436\u043e\u043d \u043f\u043e\u043a\u0438\u0434\u0430\u0435\u0442 \u0433\u043e\u0440\u043e\u0434 \u0432\u00a0\u0434\u0438\u043b\u0438\u0436\u0430\u043d\u0441\u0435, \u0438\u00a0\u043d\u0430\u0441\u0442\u0440\u043e\u0435\u043d\u043d\u044b\u0435 \u043f\u0440\u043e\u0442\u0438\u0432 \u043d\u0435\u0433\u043e \u043f\u0430\u0441\u0441\u0430\u0436\u0438\u0440\u044b \u0437\u0430\u0441\u0442\u0430\u0432\u043b\u044f\u0435\u0442 \u0435\u0433\u043e\u00a0\u0435\u0445\u0430\u0442\u044c \u0432\u043c\u0435\u0441\u0442\u0435 \u0441\u00a0\u043a\u0443\u0447\u0435\u0440\u043e\u043c. \u041d\u043e\u00a0\u043d\u0430 \u043e\u0431\u043e\u0437 \u043d\u0430\u043f\u0430\u0434\u0430\u044e\u0442 \u0440\u0430\u0437\u0431\u043e\u0439\u043d\u0438\u043a\u0438, \u0431\u0440\u043e\u0441\u0430\u044e\u0442 \u043f\u0430\u0441\u0441\u0430\u0436\u0438\u0440\u043e\u0432 \u0432\u00a0\u043f\u0443\u0441\u0442\u044b\u043d\u0435\u00a0\u0097\u00a0\u0438 \u0414\u0436\u043e\u043d \u0420\u0430\u0441\u0441\u0435\u043b \u0441\u0442\u0430\u043d\u043e\u0432\u0438\u0442\u0441\u044f \u0435\u0434\u0438\u043d\u0441\u0442\u0432\u0435\u043d\u043d\u043e\u0439 \u043d\u0430\u0434\u0435\u0436\u0434\u043e\u0439 \u044d\u0442\u0438\u0445 \u043b\u044e\u0434\u0435\u0439 \u043d\u0430\u00a0\u0441\u043f\u0430\u0441\u0435\u043d\u0438\u0435 \u0438\u00a0\u0432\u044b\u0436\u0438\u0432\u0430\u043d\u0438\u0435!", "year": 1967, "poster": "//images.kinopoisk.cloud/posters/13964.jpg", "trailer": "https://www.youtube.com/embed/kiu79Gns3c0", "age": "\u0437\u0440\u0438\u0442\u0435\u043b\u044f\u043c, \u0434\u043e\u0441\u0442\u0438\u0433\u0448\u0438\u043c 12 \u043b\u0435\u0442", "actors": ["\u041f\u043e\u043b \u041d\u044c\u044e\u043c\u0430\u043d", "\u0424\u0440\u0435\u0434\u0440\u0438\u043a \u041c\u0430\u0440\u0447", "\u0420\u0438\u0447\u0430\u0440\u0434 \u0411\u0443\u043d", "\u0414\u0430\u0439\u0430\u043d \u0427\u0438\u043b\u0435\u043d\u0442\u043e", "\u041a\u044d\u043c\u0435\u0440\u043e\u043d \u041c\u0438\u0442\u0447\u0435\u043b\u043b", "\u0411\u0430\u0440\u0431\u0430\u0440\u0430 \u0420\u0430\u0448", "\u041f\u0438\u0442\u0435\u0440 \u041b\u0430\u0437\u0435\u0440", "\u041c\u0430\u0440\u0433\u0430\u0440\u0435\u0442 \u0411\u043b\u0430\u0439", "\u041c\u0430\u0440\u0442\u0438\u043d \u0411\u043e\u043b\u0441\u0430\u043c", "\u0421\u043a\u0438\u043f \u0423\u043e\u0440\u0434"], "countries": ["\u0421\u0428\u0410"], "genres": ["\u0412\u0435\u0441\u0442\u0435\u0440\u043d"], "directors": ["\u041c\u0430\u0440\u0442\u0438\u043d \u0420\u0438\u0442\u0442"], "screenwriters": ["\u0418\u0440\u0432\u0438\u043d\u0433 \u0420\u044d\u0432\u0435\u0447", "\u0425\u0430\u0440\u0440\u0438\u0435\u0442 \u0424\u0440\u044d\u043d\u043a \u043c\u043b.", "\u042d\u043b\u043c\u043e\u0440 \u041b\u0435\u043e\u043d\u0430\u0440\u0434"], "producers": ["\u0418\u0440\u0432\u0438\u043d\u0433 \u0420\u044d\u0432\u0435\u0447", "\u041c\u0430\u0440\u0442\u0438\u043d \u0420\u0438\u0442\u0442"], "operators": ["\u0414\u0436\u0435\u0439\u043c\u0441 \u0412\u043e\u043d\u0433 \u0425\u0430\u0443"], "composers": ["\u0414\u044d\u0432\u0438\u0434 \u0420\u043e\u0443\u0437"], "painters": ["\u0414\u0436\u0435\u043a \u041c\u0430\u0440\u0442\u0438\u043d \u0421\u043c\u0438\u0442", "\u0420\u043e\u0431\u0435\u0440\u0442 \u042d\u043c\u043c\u0435\u0442 \u0421\u043c\u0438\u0442", "\u0414\u043e\u043d\u0444\u0435\u043b\u0434"], "editors": ["\u0424\u0440\u044d\u043d\u043a \u0411\u0440\u044d\u0445\u0442"], "budget": "$5860000", "rating_kinopoisk": "7.143", "rating_imdb": "7.4", "kinopoisk_votes": "570", "imdb_votes": "10580", "fees_world": null, "fees_russia": null, "premiere_world": "21 \u043c\u0430\u0440\u0442\u0430 1967", "premiere_russia": null, "frames": ["https://st.kp.yandex.net/im/kadr/1/5/9/kinopoisk.ru-Hombre-1598162.jpg", "https://st.kp.yandex.net/im/kadr/1/5/9/kinopoisk.ru-Hombre-1598163.jpg", "https://st.kp.yandex.net/im/kadr/1/5/9/kinopoisk.ru-Hombre-1598164.jpg", "https://st.kp.yandex.net/im/kadr/1/5/9/kinopoisk.ru-Hombre-1598165.jpg", "https://st.kp.yandex.net/im/kadr/2/6/2/kinopoisk.ru-Hombre-2625839.jpg", "https://st.kp.yandex.net/im/kadr/2/6/2/kinopoisk.ru-Hombre-2625840.jpg", "https://st.kp.yandex.net/im/kadr/2/6/2/kinopoisk.ru-Hombre-2625841.jpg", "https://st.kp.yandex.net/im/kadr/2/6/2/kinopoisk.ru-Hombre-2625842.jpg", "https://st.kp.yandex.net/im/kadr/2/6/2/kinopoisk.ru-Hombre-2625843.jpg", "https://st.kp.yandex.net/im/kadr/2/6/2/kinopoisk.ru-Hombre-2625844.jpg", "https://st.kp.yandex.net/im/kadr/2/6/2/kinopoisk.ru-Hombre-2625845.jpg"], "screenshots": null, "videocdn": {"url": null, "quality": null, "duration": null, "voice": null}, "hdvb": {"url": null, "quality": null, "duration": null, "voice": null}, "collapse": {"url": null, "quality": null, "duration": null, "voice": null}, "kodik": {"url": null, "quality": null, "duration": null, "voice": null}}], "pagination": {"current_page": "https://api.kinopoisk.cloud/movies/all/page/1046/token/773ef8d43c2a8c025e5ced077efa302d", "end_page": "https://api.kinopoisk.cloud/movies/all/page/59896/token/773ef8d43c2a8c025e5ced077efa302d", "total_pages": 59896}}